acctf/__init__.py
acctf/bank/__init__.py
acctf/bank/model.py
acctf/bank/mizuho/__init__.py
acctf/bank/sbi/__init__.py
acctf/bank/sbi/model.py
acctf/other/__init__.py
acctf/other/wealthnavi/__init__.py
acctf/other/wealthnavi/model.py
acctf/securities/__init__.py
acctf/securities/model.py
acctf/securities/sbi/__init__.py
acctf/securities/sbi/utils.py
acctf/utils/__init__.py
acctf/utils/format.py
acctf/utils/totp.py
acctf-0.5.5.dist-info/licenses/LICENSE
acctf-0.5.5.dist-info/METADATA
acctf-0.5.5.dist-info/WHEEL
acctf-0.5.5.dist-info/top_level.txt
acctf-0.5.5.dist-info/RECORD
