Metadata-Version: 2.4
Name: acctf
Version: 0.5.5
Summary: library that scrapes the data from an account such as securities, bank
Home-page: https://github.com/hirano00o/acctf
Author: hirano00o
Keywords: scrape,account,development
Classifier: Programming Language :: Python :: 3
Classifier: License :: OSI Approved :: MIT License
Classifier: Operating System :: OS Independent
Requires-Python: >=3.11
License-File: LICENSE
Requires-Dist: beautifulsoup4
Requires-Dist: bs4
Requires-Dist: selenium
Requires-Dist: pandas
Requires-Dist: lxml
Requires-Dist: PySocks
Requires-Dist: pyotp
Requires-Dist: html5lib
Dynamic: author
Dynamic: classifier
Dynamic: description
Dynamic: description-content-type
Dynamic: home-page
Dynamic: keywords
Dynamic: license-file
Dynamic: requires-dist
Dynamic: requires-python
Dynamic: summary
